<?xml version="1.0" encoding="UTF-8"?>
<!DOCTYPE mapper PUBLIC "-//mybatis.org//DTD Mapper 3.0//EN" "http://mybatis.org/dtd/mybatis-3-mapper.dtd">
<mapper namespace="com.erp.mapper.system.MessageMapper">

    <!-- 结果映射 -->
    <resultMap id="BaseResultMap" type="com.erp.entity.system.Message">
        <id column="消息编号" property="messageId" />
        <result column="消息类型" property="messageType" />
        <result column="消息分类" property="messageCategory" />
        <result column="消息标题" property="messageTitle" />
        <result column="消息内容" property="messageContent" />
        <result column="消息优先级" property="messagePriority" />
        <result column="接收人编码" property="receiverId" />
        <result column="发送人编码" property="senderId" />
        <result column="关联业务类型" property="businessType" />
        <result column="关联业务ID" property="businessId" />
        <result column="消息状态" property="messageStatus" />
        <result column="version" property="version" />
        <result column="创建时间" property="createTime" />
        <result column="已读时间" property="readTime" />
        <result column="删除时间" property="deleteTime" />
        <result column="备注" property="remark" />
        <result column="接收人姓名" property="receiverName" />
        <result column="发送人姓名" property="senderName" />
    </resultMap>

    <!-- 分页查询消息列表 -->
    <select id="selectMessagePage" resultMap="BaseResultMap">
        SELECT 
            m.消息编号,
            m.消息类型,
            m.消息分类,
            m.消息标题,
            m.消息内容,
            m.消息优先级,
            m.接收人编码,
            m.发送人编码,
            m.关联业务类型,
            m.关联业务ID,
            m.消息状态,
            m.创建时间,
            m.已读时间,
            m.删除时间,
            m.备注,
            receiver.员工姓名 AS 接收人姓名,
            sender.员工姓名 AS 发送人姓名
        FROM MESSAGE m
        LEFT JOIN EMPLOYEE receiver ON m.接收人编码 = receiver.员工编码
        LEFT JOIN EMPLOYEE sender ON m.发送人编码 = sender.员工编码
        WHERE m.接收人编码 = #{receiverId}
        AND m.消息状态 != '已删除'
        <if test="messageType != null and messageType != ''">
            AND m.消息类型 = #{messageType}
        </if>
        <if test="messageStatus != null and messageStatus != ''">
            AND m.消息状态 = #{messageStatus}
        </if>
        <if test="messagePriority != null and messagePriority != ''">
            AND m.消息优先级 = #{messagePriority}
        </if>
        <if test="keyword != null and keyword != ''">
            AND (m.消息标题 LIKE CONCAT('%', #{keyword}, '%') 
                 OR m.消息内容 LIKE CONCAT('%', #{keyword}, '%'))
        </if>
        ORDER BY 
            CASE m.消息优先级 
                WHEN '紧急' THEN 1 
                WHEN '高' THEN 2 
                WHEN '中' THEN 3 
                WHEN '低' THEN 4 
                ELSE 5 
            END,
            m.创建时间 DESC
    </select>

    <!-- 查询用户未读消息数量 -->
    <select id="selectUnreadCount" resultType="int">
        SELECT COUNT(*)
        FROM MESSAGE
        WHERE 接收人编码 = #{receiverId}
        AND 消息状态 = '未读'
    </select>

    <!-- 批量标记消息为已读 -->
    <update id="batchMarkAsRead">
        UPDATE MESSAGE 
        SET 消息状态 = '已读', 已读时间 = NOW()
        WHERE 消息编号 IN
        <foreach collection="messageIds" item="messageId" open="(" separator="," close=")">
            #{messageId}
        </foreach>
        AND 接收人编码 = #{receiverId}
        AND 消息状态 = '未读'
    </update>

    <!-- 批量删除消息（软删除） -->
    <update id="batchDeleteMessages">
        UPDATE MESSAGE 
        SET 消息状态 = '已删除', 删除时间 = NOW()
        WHERE 消息编号 IN
        <foreach collection="messageIds" item="messageId" open="(" separator="," close=")">
            #{messageId}
        </foreach>
        AND 接收人编码 = #{receiverId}
        AND 消息状态 != '已删除'
    </update>

    <!-- 查询消息统计信息 - 按类型统计 -->
    <select id="selectMessageStatisticsByType" resultType="map">
        SELECT 
            消息类型 AS type,
            COUNT(*) AS count
        FROM MESSAGE
        WHERE 接收人编码 = #{receiverId}
        AND 消息状态 != '已删除'
        GROUP BY 消息类型
    </select>

    <!-- 查询未读消息统计信息 - 按类型统计 -->
    <select id="selectUnreadStatisticsByType" resultType="map">
        SELECT 
            消息类型 AS type,
            COUNT(*) AS count
        FROM MESSAGE
        WHERE 接收人编码 = #{receiverId}
        AND 消息状态 = '未读'
        GROUP BY 消息类型
    </select>

    <!-- 查询消息统计信息 - 按优先级统计 -->
    <select id="selectMessageStatisticsByPriority" resultType="map">
        SELECT 
            消息优先级 AS priority,
            COUNT(*) AS count
        FROM MESSAGE
        WHERE 接收人编码 = #{receiverId}
        AND 消息状态 != '已删除'
        GROUP BY 消息优先级
    </select>

    <!-- 查询消息统计信息 - 按状态统计 -->
    <select id="selectMessageStatisticsByStatus" resultType="map">
        SELECT 
            消息状态 AS status,
            COUNT(*) AS count
        FROM MESSAGE
        WHERE 接收人编码 = #{receiverId}
        AND 消息状态 != '已删除'
        GROUP BY 消息状态
    </select>

    <!-- 查询消息总数 -->
    <select id="selectMessageTotalCount" resultType="int">
        SELECT COUNT(*)
        FROM MESSAGE
        WHERE 接收人编码 = #{receiverId}
        AND 消息状态 != '已删除'
    </select>

    <!-- 查询所有未读消息ID -->
    <select id="selectAllUnreadMessageIds" resultType="int">
        SELECT 消息编号
        FROM MESSAGE
        WHERE 接收人编码 = #{receiverId}
        AND 消息状态 = '未读'
    </select>

    <!-- 查询所有消息ID（用于清空） -->
    <select id="selectAllMessageIds" resultType="int">
        SELECT 消息编号
        FROM MESSAGE
        WHERE 接收人编码 = #{receiverId}
        AND 消息状态 != '已删除'
    </select>

    <!-- 全部标记为已读 -->
    <update id="markAllAsRead">
        UPDATE MESSAGE 
        SET 消息状态 = '已读', 已读时间 = NOW()
        WHERE 接收人编码 = #{receiverId}
        AND 消息状态 = '未读'
    </update>

    <!-- 清空所有消息（软删除） -->
    <update id="clearAllMessages">
        UPDATE MESSAGE 
        SET 消息状态 = '已删除', 删除时间 = NOW()
        WHERE 接收人编码 = #{receiverId}
        AND 消息状态 != '已删除'
    </update>

</mapper>

































